{"metar": [{"icaoId": "KPDK", "receiptTime": "2026-04-12T04:56:28.433Z", "obsTime": 1775969580, "reportTime": "2026-04-12T05:00:00.000Z", "temp": 14.4, "dewp": 7.8, "wdir": 0, "wspd": 0, "visib": 9, "altim": 1024.8, "slp": 1023.4, "qcField": 12, "maxT24": 32.2, "minT24": 9.4, "metarType": "METAR", "rawOb": "METAR KPDK 120453Z 00000KT 9SM CLR 14/08 A3026 RMK AO2 SLP234 T01440078 403220094 $", "lat": 33.8783, "lon": -84.298, "elev": 299, "name": "Atlanta/Dekalb-Peachtree Arpt, GA, US", "cover": "CLR", "clouds": [], "fltCat": "VFR"}], "taf": [{"icaoId": "KPDK", "dbPopTime": "2026-04-12T05:21:39.439Z", "bulletinTime": "2026-04-12T05:21:00.000Z", "issueTime": "2026-04-12T05:21:00.000Z", "validTimeFrom": 1775973600, "validTimeTo": 1776060000, "rawTAF": "TAF KPDK 120521Z 1206/1306 VRB03KT P6SM SKC FM121500 18005KT P6SM FEW250 FM121900 17008KT P6SM SKC", "mostRecent": 1, "remarks": "", "lat": 33.87835, "lon": -84.29801, "elev": 299, "prior": 6, "name": "Atlanta/Dekalb-Peachtree Arpt", "fcsts": [{"timeFrom": 1775973600, "timeTo": 1776006000, "timeBec": null, "fcstChange": null, "probability": null, "wdir": "VRB", "wspd": 3, "wgst": null, "wshearHgt": null, "wshearDir": null, "wshearSpd": null, "visib": "6+", "altim": null, "vertVis": null, "wxString": null, "notDecoded": null, "clouds": [{"cover": "SKC", "base": null, "type": null}], "icgTurb": [], "temp": []}, {"timeFrom": 1776006000, "timeTo": 1776020400, "timeBec": null, "fcstChange": "FM", "probability": null, "wdir": 180, "wspd": 5, "wgst": null, "wshearHgt": null, "wshearDir": null, "wshearSpd": null, "visib": "6+", "altim": null, "vertVis": null, "wxString": null, "notDecoded": null, "clouds": [{"cover": "FEW", "base": 25000, "type": null}], "icgTurb": [], "temp": []}, {"timeFrom": 1776020400, "timeTo": 1776060000, "timeBec": null, "fcstChange": "FM", "probability": null, "wdir": 170, "wspd": 8, "wgst": null, "wshearHgt": null, "wshearDir": null, "wshearSpd": null, "visib": "6+", "altim": null, "vertVis": null, "wxString": null, "notDecoded": null, "clouds": [{"cover": "SKC", "base": null, "type": null}], "icgTurb": [], "temp": []}]}]}