{"metar": [{"icaoId": "KPDK", "receiptTime": "2026-04-11T23:56:26.637Z", "obsTime": 1775951580, "reportTime": "2026-04-12T00:00:00.000Z", "temp": 26.1, "dewp": 4.4, "wdir": 260, "wspd": 4, "visib": "10+", "altim": 1024.1, "slp": 1023, "qcField": 12, "presTend": 0.1, "maxT": 32.2, "minT": 26.1, "metarType": "METAR", "rawOb": "METAR KPDK 112353Z 26004KT 10SM CLR 26/04 A3024 RMK AO2 SLP230 T02610044 10322 20261 53001 $", "lat": 33.8783, "lon": -84.298, "elev": 299, "name": "Atlanta/Dekalb-Peachtree Arpt, GA, US", "cover": "CLR", "clouds": [], "fltCat": "VFR"}], "taf": [{"icaoId": "KPDK", "dbPopTime": "2026-04-11T23:33:55.933Z", "bulletinTime": "2026-04-11T23:33:00.000Z", "issueTime": "2026-04-11T23:33:00.000Z", "validTimeFrom": 1775952000, "validTimeTo": 1776038400, "rawTAF": "TAF KPDK 112333Z 1200/1224 VRB03KT P6SM SKC FM121600 17005KT P6SM SKC FM121800 16007KT P6SM SKC", "mostRecent": 1, "remarks": "", "lat": 33.87835, "lon": -84.29801, "elev": 299, "prior": 6, "name": "Atlanta/Dekalb-Peachtree Arpt", "fcsts": [{"timeFrom": 1775952000, "timeTo": 1776009600, "timeBec": null, "fcstChange": null, "probability": null, "wdir": "VRB", "wspd": 3, "wgst": null, "wshearHgt": null, "wshearDir": null, "wshearSpd": null, "visib": "6+", "altim": null, "vertVis": null, "wxString": null, "notDecoded": null, "clouds": [{"cover": "SKC", "base": null, "type": null}], "icgTurb": [], "temp": []}, {"timeFrom": 1776009600, "timeTo": 1776016800, "timeBec": null, "fcstChange": "FM", "probability": null, "wdir": 170, "wspd": 5, "wgst": null, "wshearHgt": null, "wshearDir": null, "wshearSpd": null, "visib": "6+", "altim": null, "vertVis": null, "wxString": null, "notDecoded": null, "clouds": [{"cover": "SKC", "base": null, "type": null}], "icgTurb": [], "temp": []}, {"timeFrom": 1776016800, "timeTo": 1776038400, "timeBec": null, "fcstChange": "FM", "probability": null, "wdir": 160, "wspd": 7, "wgst": null, "wshearHgt": null, "wshearDir": null, "wshearSpd": null, "visib": "6+", "altim": null, "vertVis": null, "wxString": null, "notDecoded": null, "clouds": [{"cover": "SKC", "base": null, "type": null}], "icgTurb": [], "temp": []}]}]}